{
    "donated": true,
    "date_published": 1679011200,
    "name": "Machete",
    "type": 2,
    "info": null,
    "authors": {
        "Ulan Cabanilla": "All"
    },
    "files_hash": "b0c3f65142f2cebb4ea081fbface08a50d729359",
    "categories": [
        "props",
        "collection: the_shed"
    ],
    "tags": [
        "weapon",
        "knife",
        "iron",
        "steel",
        "shed",
        "gardening",
        "metal",
        "jungle",
        "blade",
        "sharp",
        "survival",
        "tool",
        "combat"
    ],
    "max_resolution": [
        4096,
        4096
    ],
    "polycount": 3032,
    "texel_density": 11365.22978788816,
    "dimensions": [
        44.37695816159248,
        61.11501157283783,
        754.8029869794846
    ],
    "download_count": 3742,
    "thumbnail_url": "https://cdn.polyhaven.com/asset_img/thumbs/machete.png?width=256&height=256",
    "files": {
        "Diffuse": {
            "4k": {
                "jpg": {
                    "size": 10621313,
                    "url": "https://dl.polyhaven.org/file/ph-assets/Models/jpg/4k/machete/machete_diff_4k.jpg",
                    "md5": "6758725bfcf808e885d5100082398898"
                },
                "png": {
                    "size": 48196273,
                    "url": "https://dl.polyhaven.org/file/ph-assets/Models/png/4k/machete/machete_diff_4k.png",
                    "md5": "460bbe68bd0cece05824120fe85881da"
                },
                "exr": {
                    "size": 20566939,
                    "url": "https://dl.polyhaven.org/file/ph-assets/Models/exr/4k/machete/machete_diff_4k.exr",
                    "md5": "2fec588ae2c6c16740291bbeba5e8f8a"
                }
            },
            "2k": {
                "jpg": {
                    "size": 2687965,
                    "url": "https://dl.polyhaven.org/file/ph-assets/Models/jpg/2k/machete/machete_diff_2k.jpg",
                    "md5": "5688b97b0425d6507c60ed001de18f34"
                },
                "png": {
                    "size": 14541129,
                    "url": "https://dl.polyhaven.org/file/ph-assets/Models/png/2k/machete/machete_diff_2k.png",
                    "md5": "fcf7cb39c7fd0abe7fbd8a78e5fc7b52"
                },
                "exr": {
                    "size": 5149810,
                    "url": "https://dl.polyhaven.org/file/ph-assets/Models/exr/2k/machete/machete_diff_2k.exr",
                    "md5": "4b825fb3c30ba95af05eb19c691688d1"
                }
            },
            "1k": {
                "jpg": {
                    "size": 679468,
                    "url": "https://dl.polyhaven.org/file/ph-assets/Models/jpg/1k/machete/machete_diff_1k.jpg",
                    "md5": "fd61e44d808059acfd354f9167ad4e65"
                },
                "png": {
                    "size": 4032379,
                    "url": "https://dl.polyhaven.org/file/ph-assets/Models/png/1k/machete/machete_diff_1k.png",
                    "md5": "5234d56a6b3f5c52e1ddacda5a95585f"
                },
                "exr": {
                    "size": 1331183,
                    "url": "https://dl.polyhaven.org/file/ph-assets/Models/exr/1k/machete/machete_diff_1k.exr",
                    "md5": "6ed32cde0be446741cad295c280a84e6"
                }
            }
        },
        "nor_dx": {
            "4k": {
                "jpg": {
                    "size": 15827511,
                    "url": "https://dl.polyhaven.org/file/ph-assets/Models/jpg/4k/machete/machete_nor_dx_4k.jpg",
                    "md5": "d7ed4ee3b5059e53c180fc65b8536959"
                },
                "png": {
                    "size": 56314149,
                    "url": "https://dl.polyhaven.org/file/ph-assets/Models/png/4k/machete/machete_nor_dx_4k.png",
                    "md5": "2daad219695f5d12d9a972c1ba3e2790"
                },
                "exr": {
                    "size": 30830164,
                    "url": "https://dl.polyhaven.org/file/ph-assets/Models/exr/4k/machete/machete_nor_dx_4k.exr",
                    "md5": "0907b13bbba27c2230c87e43068ac3d7"
                }
            },
            "2k": {
                "jpg": {
                    "size": 3979928,
                    "url": "https://dl.polyhaven.org/file/ph-assets/Models/jpg/2k/machete/machete_nor_dx_2k.jpg",
                    "md5": "40f672801fd29eed00307f02bbc1b003"
                },
                "png": {
                    "size": 15289492,
                    "url": "https://dl.polyhaven.org/file/ph-assets/Models/png/2k/machete/machete_nor_dx_2k.png",
                    "md5": "fb3118ef4058d31c391b76e3a7ccc9c4"
                },
                "exr": {
                    "size": 8188928,
                    "url": "https://dl.polyhaven.org/file/ph-assets/Models/exr/2k/machete/machete_nor_dx_2k.exr",
                    "md5": "0ee07d9eb2c6ccfdb50f6ea0eb614e4a"
                }
            },
            "1k": {
                "jpg": {
                    "size": 927126,
                    "url": "https://dl.polyhaven.org/file/ph-assets/Models/jpg/1k/machete/machete_nor_dx_1k.jpg",
                    "md5": "84364ab9f09e72a3d0d0025b8da23086"
                },
                "png": {
                    "size": 4134929,
                    "url": "https://dl.polyhaven.org/file/ph-assets/Models/png/1k/machete/machete_nor_dx_1k.png",
                    "md5": "d40dd0cd5ec5097e8239eb3475582252"
                },
                "exr": {
                    "size": 2034768,
                    "url": "https://dl.polyhaven.org/file/ph-assets/Models/exr/1k/machete/machete_nor_dx_1k.exr",
                    "md5": "edeb44a72ec5259bb96d517e52bbeae3"
                }
            }
        },
        "nor_gl": {
            "4k": {
                "jpg": {
                    "size": 15681163,
                    "url": "https://dl.polyhaven.org/file/ph-assets/Models/jpg/4k/machete/machete_nor_gl_4k.jpg",
                    "md5": "4126098dff7c41ed3c5d3adac335ba00"
                },
                "png": {
                    "size": 56314506,
                    "url": "https://dl.polyhaven.org/file/ph-assets/Models/png/4k/machete/machete_nor_gl_4k.png",
                    "md5": "57b7845e9caebab14d883c0eb4a7cb2e"
                },
                "exr": {
                    "size": 30824331,
                    "url": "https://dl.polyhaven.org/file/ph-assets/Models/exr/4k/machete/machete_nor_gl_4k.exr",
                    "md5": "1acb35dc0f56847f6761639d4903735b"
                }
            },
            "2k": {
                "jpg": {
                    "size": 3944271,
                    "url": "https://dl.polyhaven.org/file/ph-assets/Models/jpg/2k/machete/machete_nor_gl_2k.jpg",
                    "md5": "5526b2a66b67a3bcde35fe2a9f84061f"
                },
                "png": {
                    "size": 15290415,
                    "url": "https://dl.polyhaven.org/file/ph-assets/Models/png/2k/machete/machete_nor_gl_2k.png",
                    "md5": "5b9f53368842d24731a0ad1709e0674e"
                },
                "exr": {
                    "size": 8194498,
                    "url": "https://dl.polyhaven.org/file/ph-assets/Models/exr/2k/machete/machete_nor_gl_2k.exr",
                    "md5": "c421a169745b27ffc1b2cc75090bf5e4"
                }
            },
            "1k": {
                "jpg": {
                    "size": 915855,
                    "url": "https://dl.polyhaven.org/file/ph-assets/Models/jpg/1k/machete/machete_nor_gl_1k.jpg",
                    "md5": "44296250fa2540af75c2e351659adeb4"
                },
                "png": {
                    "size": 4134324,
                    "url": "https://dl.polyhaven.org/file/ph-assets/Models/png/1k/machete/machete_nor_gl_1k.png",
                    "md5": "633c8299b91bb3a9d6fc177142c50477"
                },
                "exr": {
                    "size": 2036538,
                    "url": "https://dl.polyhaven.org/file/ph-assets/Models/exr/1k/machete/machete_nor_gl_1k.exr",
                    "md5": "9c30b72bee52780a20671e67f09fd4c6"
                }
            }
        },
        "blend": {
            "4k": {
                "blend": {
                    "include": {
                        "textures/machete_diff_4k.jpg": {
                            "size": 10621313,
                            "url": "https://dl.polyhaven.org/file/ph-assets/Models/jpg/4k/machete/machete_diff_4k.jpg",
                            "md5": "6758725bfcf808e885d5100082398898"
                        },
                        "textures/machete_metal_4k.exr": {
                            "size": 5631995,
                            "url": "https://dl.polyhaven.org/file/ph-assets/Models/exr/4k/machete/machete_metal_4k.exr",
                            "md5": "4fa6bffad167cbd26b2dba5ad0ba2a41"
                        },
                        "textures/machete_rough_4k.exr": {
                            "size": 11903675,
                            "url": "https://dl.polyhaven.org/file/ph-assets/Models/exr/4k/machete/machete_rough_4k.exr",
                            "md5": "dc6992550c93bc2bb1976358b2cd4a82"
                        },
                        "textures/machete_nor_gl_4k.exr": {
                            "size": 30824331,
                            "url": "https://dl.polyhaven.org/file/ph-assets/Models/exr/4k/machete/machete_nor_gl_4k.exr",
                            "md5": "1acb35dc0f56847f6761639d4903735b"
                        }
                    },
                    "size": 213731,
                    "url": "https://dl.polyhaven.org/file/ph-assets/Models/blend/4k/machete/machete_4k.blend",
                    "md5": "5da0b2ab3cd90ed096e96b6b2fe31cb8"
                }
            },
            "2k": {
                "blend": {
                    "include": {
                        "textures/machete_nor_gl_2k.exr": {
                            "size": 8194498,
                            "url": "https://dl.polyhaven.org/file/ph-assets/Models/exr/2k/machete/machete_nor_gl_2k.exr",
                            "md5": "c421a169745b27ffc1b2cc75090bf5e4"
                        },
                        "textures/machete_metal_2k.exr": {
                            "size": 1739682,
                            "url": "https://dl.polyhaven.org/file/ph-assets/Models/exr/2k/machete/machete_metal_2k.exr",
                            "md5": "275ca55363de496c8c156822bbb5df15"
                        },
                        "textures/machete_rough_2k.exr": {
                            "size": 3538397,
                            "url": "https://dl.polyhaven.org/file/ph-assets/Models/exr/2k/machete/machete_rough_2k.exr",
                            "md5": "d9764d6b013a343ea22728bac2b712f4"
                        },
                        "textures/machete_diff_2k.jpg": {
                            "size": 2687965,
                            "url": "https://dl.polyhaven.org/file/ph-assets/Models/jpg/2k/machete/machete_diff_2k.jpg",
                            "md5": "5688b97b0425d6507c60ed001de18f34"
                        }
                    },
                    "size": 213950,
                    "url": "https://dl.polyhaven.org/file/ph-assets/Models/blend/2k/machete/machete_2k.blend",
                    "md5": "6a363b71f98e00b8c1dbdbd2f65527cd"
                }
            },
            "1k": {
                "blend": {
                    "include": {
                        "textures/machete_diff_1k.jpg": {
                            "size": 679468,
                            "url": "https://dl.polyhaven.org/file/ph-assets/Models/jpg/1k/machete/machete_diff_1k.jpg",
                            "md5": "fd61e44d808059acfd354f9167ad4e65"
                        },
                        "textures/machete_metal_1k.exr": {
                            "size": 509369,
                            "url": "https://dl.polyhaven.org/file/ph-assets/Models/exr/1k/machete/machete_metal_1k.exr",
                            "md5": "80f4c246cebd7798a12786774dbfe2db"
                        },
                        "textures/machete_rough_1k.exr": {
                            "size": 997316,
                            "url": "https://dl.polyhaven.org/file/ph-assets/Models/exr/1k/machete/machete_rough_1k.exr",
                            "md5": "cf46ac08bade06d275dfcd6febb76885"
                        },
                        "textures/machete_nor_gl_1k.exr": {
                            "size": 2036538,
                            "url": "https://dl.polyhaven.org/file/ph-assets/Models/exr/1k/machete/machete_nor_gl_1k.exr",
                            "md5": "9c30b72bee52780a20671e67f09fd4c6"
                        }
                    },
                    "size": 213954,
                    "url": "https://dl.polyhaven.org/file/ph-assets/Models/blend/1k/machete/machete_1k.blend",
                    "md5": "cb65875c6fc0fae1aec9274cb7f26651"
                }
            }
        },
        "gltf": {
            "4k": {
                "gltf": {
                    "include": {
                        "textures/machete_diff_4k.jpg": {
                            "size": 10621313,
                            "url": "https://dl.polyhaven.org/file/ph-assets/Models/jpg/4k/machete/machete_diff_4k.jpg",
                            "md5": "6758725bfcf808e885d5100082398898"
                        },
                        "machete.bin": {
                            "size": 74416,
                            "url": "https://dl.polyhaven.org/file/ph-assets/Models/gltf/4k/machete/machete.bin",
                            "md5": "e99f50b307fc2fce13409445a38b282e"
                        },
                        "textures/machete_arm_4k.jpg": {
                            "size": 11626393,
                            "url": "https://dl.polyhaven.org/file/ph-assets/Models/jpg/4k/machete/machete_arm_4k.jpg",
                            "md5": "1926d8f53acc5dced96de565125d33f2"
                        },
                        "textures/machete_nor_gl_4k.jpg": {
                            "size": 15681163,
                            "url": "https://dl.polyhaven.org/file/ph-assets/Models/jpg/4k/machete/machete_nor_gl_4k.jpg",
                            "md5": "4126098dff7c41ed3c5d3adac335ba00"
                        }
                    },
                    "size": 2716,
                    "url": "https://dl.polyhaven.org/file/ph-assets/Models/gltf/4k/machete/machete_4k.gltf",
                    "md5": "250fd27d08cce0976c33f65527729ceb"
                }
            },
            "2k": {
                "gltf": {
                    "include": {
                        "machete.bin": {
                            "size": 74416,
                            "url": "https://dl.polyhaven.org/file/ph-assets/Models/gltf/4k/machete/machete.bin",
                            "md5": "e99f50b307fc2fce13409445a38b282e"
                        },
                        "textures/machete_nor_gl_2k.jpg": {
                            "size": 3944271,
                            "url": "https://dl.polyhaven.org/file/ph-assets/Models/jpg/2k/machete/machete_nor_gl_2k.jpg",
                            "md5": "5526b2a66b67a3bcde35fe2a9f84061f"
                        },
                        "textures/machete_arm_2k.jpg": {
                            "size": 2998014,
                            "url": "https://dl.polyhaven.org/file/ph-assets/Models/jpg/2k/machete/machete_arm_2k.jpg",
                            "md5": "d9f948421579d84fc709999f32545277"
                        },
                        "textures/machete_diff_2k.jpg": {
                            "size": 2687965,
                            "url": "https://dl.polyhaven.org/file/ph-assets/Models/jpg/2k/machete/machete_diff_2k.jpg",
                            "md5": "5688b97b0425d6507c60ed001de18f34"
                        }
                    },
                    "size": 2716,
                    "url": "https://dl.polyhaven.org/file/ph-assets/Models/gltf/2k/machete/machete_2k.gltf",
                    "md5": "379fc03984262ce1d75ecb8aed3904b8"
                }
            },
            "1k": {
                "gltf": {
                    "include": {
                        "textures/machete_nor_gl_1k.jpg": {
                            "size": 915855,
                            "url": "https://dl.polyhaven.org/file/ph-assets/Models/jpg/1k/machete/machete_nor_gl_1k.jpg",
                            "md5": "44296250fa2540af75c2e351659adeb4"
                        },
                        "textures/machete_diff_1k.jpg": {
                            "size": 679468,
                            "url": "https://dl.polyhaven.org/file/ph-assets/Models/jpg/1k/machete/machete_diff_1k.jpg",
                            "md5": "fd61e44d808059acfd354f9167ad4e65"
                        },
                        "machete.bin": {
                            "size": 74416,
                            "url": "https://dl.polyhaven.org/file/ph-assets/Models/gltf/4k/machete/machete.bin",
                            "md5": "e99f50b307fc2fce13409445a38b282e"
                        },
                        "textures/machete_arm_1k.jpg": {
                            "size": 752047,
                            "url": "https://dl.polyhaven.org/file/ph-assets/Models/jpg/1k/machete/machete_arm_1k.jpg",
                            "md5": "7e6e936108601a0956526f33aeac50ce"
                        }
                    },
                    "size": 2716,
                    "url": "https://dl.polyhaven.org/file/ph-assets/Models/gltf/1k/machete/machete_1k.gltf",
                    "md5": "4ce7757182dca2b9b2324ce882140d4a"
                }
            }
        },
        "usd": {
            "4k": {
                "usd": {
                    "include": {
                        "textures/machete_diff_4k.jpg": {
                            "size": 10621313,
                            "url": "https://dl.polyhaven.org/file/ph-assets/Models/jpg/4k/machete/machete_diff_4k.jpg",
                            "md5": "6758725bfcf808e885d5100082398898"
                        },
                        "textures/machete_metal_4k.exr": {
                            "size": 5631995,
                            "url": "https://dl.polyhaven.org/file/ph-assets/Models/exr/4k/machete/machete_metal_4k.exr",
                            "md5": "4fa6bffad167cbd26b2dba5ad0ba2a41"
                        },
                        "textures/machete_rough_4k.exr": {
                            "size": 11903675,
                            "url": "https://dl.polyhaven.org/file/ph-assets/Models/exr/4k/machete/machete_rough_4k.exr",
                            "md5": "dc6992550c93bc2bb1976358b2cd4a82"
                        },
                        "textures/machete_nor_gl_4k.exr": {
                            "size": 30824331,
                            "url": "https://dl.polyhaven.org/file/ph-assets/Models/exr/4k/machete/machete_nor_gl_4k.exr",
                            "md5": "1acb35dc0f56847f6761639d4903735b"
                        }
                    },
                    "size": 150037,
                    "url": "https://dl.polyhaven.org/file/ph-assets/Models/usd/4k/machete/machete_4k.usdc",
                    "md5": "e007d05a305752664053fef9d3359657"
                }
            },
            "2k": {
                "usd": {
                    "include": {
                        "textures/machete_nor_gl_2k.exr": {
                            "size": 8194498,
                            "url": "https://dl.polyhaven.org/file/ph-assets/Models/exr/2k/machete/machete_nor_gl_2k.exr",
                            "md5": "c421a169745b27ffc1b2cc75090bf5e4"
                        },
                        "textures/machete_metal_2k.exr": {
                            "size": 1739682,
                            "url": "https://dl.polyhaven.org/file/ph-assets/Models/exr/2k/machete/machete_metal_2k.exr",
                            "md5": "275ca55363de496c8c156822bbb5df15"
                        },
                        "textures/machete_rough_2k.exr": {
                            "size": 3538397,
                            "url": "https://dl.polyhaven.org/file/ph-assets/Models/exr/2k/machete/machete_rough_2k.exr",
                            "md5": "d9764d6b013a343ea22728bac2b712f4"
                        },
                        "textures/machete_diff_2k.jpg": {
                            "size": 2687965,
                            "url": "https://dl.polyhaven.org/file/ph-assets/Models/jpg/2k/machete/machete_diff_2k.jpg",
                            "md5": "5688b97b0425d6507c60ed001de18f34"
                        }
                    },
                    "size": 150037,
                    "url": "https://dl.polyhaven.org/file/ph-assets/Models/usd/2k/machete/machete_2k.usdc",
                    "md5": "2540a34266a665804c3d3bdbfee75268"
                }
            },
            "1k": {
                "usd": {
                    "include": {
                        "textures/machete_diff_1k.jpg": {
                            "size": 679468,
                            "url": "https://dl.polyhaven.org/file/ph-assets/Models/jpg/1k/machete/machete_diff_1k.jpg",
                            "md5": "fd61e44d808059acfd354f9167ad4e65"
                        },
                        "textures/machete_metal_1k.exr": {
                            "size": 509369,
                            "url": "https://dl.polyhaven.org/file/ph-assets/Models/exr/1k/machete/machete_metal_1k.exr",
                            "md5": "80f4c246cebd7798a12786774dbfe2db"
                        },
                        "textures/machete_rough_1k.exr": {
                            "size": 997316,
                            "url": "https://dl.polyhaven.org/file/ph-assets/Models/exr/1k/machete/machete_rough_1k.exr",
                            "md5": "cf46ac08bade06d275dfcd6febb76885"
                        },
                        "textures/machete_nor_gl_1k.exr": {
                            "size": 2036538,
                            "url": "https://dl.polyhaven.org/file/ph-assets/Models/exr/1k/machete/machete_nor_gl_1k.exr",
                            "md5": "9c30b72bee52780a20671e67f09fd4c6"
                        }
                    },
                    "size": 150037,
                    "url": "https://dl.polyhaven.org/file/ph-assets/Models/usd/1k/machete/machete_1k.usdc",
                    "md5": "98cecb15cdea93f47d60158bd2b1d190"
                }
            }
        },
        "Metal": {
            "4k": {
                "jpg": {
                    "size": 5357897,
                    "url": "https://dl.polyhaven.org/file/ph-assets/Models/jpg/4k/machete/machete_metal_4k.jpg",
                    "md5": "852235dc7cb6dd1c0314a2f33a310be4"
                },
                "png": {
                    "size": 6276101,
                    "url": "https://dl.polyhaven.org/file/ph-assets/Models/png/4k/machete/machete_metal_4k.png",
                    "md5": "65f8878e52a6a8f2b207a7ed49ff7b26"
                },
                "exr": {
                    "size": 5631995,
                    "url": "https://dl.polyhaven.org/file/ph-assets/Models/exr/4k/machete/machete_metal_4k.exr",
                    "md5": "4fa6bffad167cbd26b2dba5ad0ba2a41"
                }
            },
            "2k": {
                "jpg": {
                    "size": 1483393,
                    "url": "https://dl.polyhaven.org/file/ph-assets/Models/jpg/2k/machete/machete_metal_2k.jpg",
                    "md5": "fa539eced7a67df4edc7d0eea0c7403b"
                },
                "png": {
                    "size": 2057628,
                    "url": "https://dl.polyhaven.org/file/ph-assets/Models/png/2k/machete/machete_metal_2k.png",
                    "md5": "96059447e53785497a54814667ee78fd"
                },
                "exr": {
                    "size": 1739682,
                    "url": "https://dl.polyhaven.org/file/ph-assets/Models/exr/2k/machete/machete_metal_2k.exr",
                    "md5": "275ca55363de496c8c156822bbb5df15"
                }
            },
            "1k": {
                "jpg": {
                    "size": 402416,
                    "url": "https://dl.polyhaven.org/file/ph-assets/Models/jpg/1k/machete/machete_metal_1k.jpg",
                    "md5": "0141d55409b79e22cb9c0c97fec1adc5"
                },
                "png": {
                    "size": 602582,
                    "url": "https://dl.polyhaven.org/file/ph-assets/Models/png/1k/machete/machete_metal_1k.png",
                    "md5": "9607ecc8479d46b5fbec7b1d5f962bad"
                },
                "exr": {
                    "size": 509369,
                    "url": "https://dl.polyhaven.org/file/ph-assets/Models/exr/1k/machete/machete_metal_1k.exr",
                    "md5": "80f4c246cebd7798a12786774dbfe2db"
                }
            }
        },
        "fbx": {
            "4k": {
                "fbx": {
                    "include": {
                        "textures/machete_diff_4k.jpg": {
                            "size": 10621313,
                            "url": "https://dl.polyhaven.org/file/ph-assets/Models/jpg/4k/machete/machete_diff_4k.jpg",
                            "md5": "6758725bfcf808e885d5100082398898"
                        },
                        "textures/machete_metal_4k.exr": {
                            "size": 5631995,
                            "url": "https://dl.polyhaven.org/file/ph-assets/Models/exr/4k/machete/machete_metal_4k.exr",
                            "md5": "4fa6bffad167cbd26b2dba5ad0ba2a41"
                        },
                        "textures/machete_rough_4k.exr": {
                            "size": 11903675,
                            "url": "https://dl.polyhaven.org/file/ph-assets/Models/exr/4k/machete/machete_rough_4k.exr",
                            "md5": "dc6992550c93bc2bb1976358b2cd4a82"
                        },
                        "textures/machete_nor_gl_4k.exr": {
                            "size": 30824331,
                            "url": "https://dl.polyhaven.org/file/ph-assets/Models/exr/4k/machete/machete_nor_gl_4k.exr",
                            "md5": "1acb35dc0f56847f6761639d4903735b"
                        }
                    },
                    "size": 113036,
                    "url": "https://dl.polyhaven.org/file/ph-assets/Models/fbx/4k/machete/machete_4k.fbx",
                    "md5": "c9345cf5081cbeea3e7467385c4258b2"
                }
            },
            "2k": {
                "fbx": {
                    "include": {
                        "textures/machete_metal_2k.exr": {
                            "size": 1739682,
                            "url": "https://dl.polyhaven.org/file/ph-assets/Models/exr/2k/machete/machete_metal_2k.exr",
                            "md5": "275ca55363de496c8c156822bbb5df15"
                        },
                        "textures/machete_nor_gl_2k.exr": {
                            "size": 8194498,
                            "url": "https://dl.polyhaven.org/file/ph-assets/Models/exr/2k/machete/machete_nor_gl_2k.exr",
                            "md5": "c421a169745b27ffc1b2cc75090bf5e4"
                        },
                        "textures/machete_rough_2k.exr": {
                            "size": 3538397,
                            "url": "https://dl.polyhaven.org/file/ph-assets/Models/exr/2k/machete/machete_rough_2k.exr",
                            "md5": "d9764d6b013a343ea22728bac2b712f4"
                        },
                        "textures/machete_diff_2k.jpg": {
                            "size": 2687965,
                            "url": "https://dl.polyhaven.org/file/ph-assets/Models/jpg/2k/machete/machete_diff_2k.jpg",
                            "md5": "5688b97b0425d6507c60ed001de18f34"
                        }
                    },
                    "size": 113036,
                    "url": "https://dl.polyhaven.org/file/ph-assets/Models/fbx/2k/machete/machete_2k.fbx",
                    "md5": "8cb2544f592efda88b70dd67b416d317"
                }
            },
            "1k": {
                "fbx": {
                    "include": {
                        "textures/machete_diff_1k.jpg": {
                            "size": 679468,
                            "url": "https://dl.polyhaven.org/file/ph-assets/Models/jpg/1k/machete/machete_diff_1k.jpg",
                            "md5": "fd61e44d808059acfd354f9167ad4e65"
                        },
                        "textures/machete_metal_1k.exr": {
                            "size": 509369,
                            "url": "https://dl.polyhaven.org/file/ph-assets/Models/exr/1k/machete/machete_metal_1k.exr",
                            "md5": "80f4c246cebd7798a12786774dbfe2db"
                        },
                        "textures/machete_rough_1k.exr": {
                            "size": 997316,
                            "url": "https://dl.polyhaven.org/file/ph-assets/Models/exr/1k/machete/machete_rough_1k.exr",
                            "md5": "cf46ac08bade06d275dfcd6febb76885"
                        },
                        "textures/machete_nor_gl_1k.exr": {
                            "size": 2036538,
                            "url": "https://dl.polyhaven.org/file/ph-assets/Models/exr/1k/machete/machete_nor_gl_1k.exr",
                            "md5": "9c30b72bee52780a20671e67f09fd4c6"
                        }
                    },
                    "size": 113036,
                    "url": "https://dl.polyhaven.org/file/ph-assets/Models/fbx/1k/machete/machete_1k.fbx",
                    "md5": "07f8c362998bda2d226bcaca0ebf5bc1"
                }
            }
        },
        "arm": {
            "4k": {
                "jpg": {
                    "size": 11626393,
                    "url": "https://dl.polyhaven.org/file/ph-assets/Models/jpg/4k/machete/machete_arm_4k.jpg",
                    "md5": "1926d8f53acc5dced96de565125d33f2"
                },
                "png": {
                    "size": 31383789,
                    "url": "https://dl.polyhaven.org/file/ph-assets/Models/png/4k/machete/machete_arm_4k.png",
                    "md5": "0df7565cb3bf6807ca18bbffffe9a2ce"
                },
                "exr": {
                    "size": 25527940,
                    "url": "https://dl.polyhaven.org/file/ph-assets/Models/exr/4k/machete/machete_arm_4k.exr",
                    "md5": "9945012b50865d5d22a39c33044708c5"
                }
            },
            "2k": {
                "jpg": {
                    "size": 2998014,
                    "url": "https://dl.polyhaven.org/file/ph-assets/Models/jpg/2k/machete/machete_arm_2k.jpg",
                    "md5": "d9f948421579d84fc709999f32545277"
                },
                "png": {
                    "size": 10749453,
                    "url": "https://dl.polyhaven.org/file/ph-assets/Models/png/2k/machete/machete_arm_2k.png",
                    "md5": "f04290f3566f156d29e3c082174cc4ff"
                },
                "exr": {
                    "size": 6851365,
                    "url": "https://dl.polyhaven.org/file/ph-assets/Models/exr/2k/machete/machete_arm_2k.exr",
                    "md5": "932dfa4cbc3f54d7ea0cb6eb3abbad66"
                }
            },
            "1k": {
                "jpg": {
                    "size": 752047,
                    "url": "https://dl.polyhaven.org/file/ph-assets/Models/jpg/1k/machete/machete_arm_1k.jpg",
                    "md5": "7e6e936108601a0956526f33aeac50ce"
                },
                "png": {
                    "size": 3145725,
                    "url": "https://dl.polyhaven.org/file/ph-assets/Models/png/1k/machete/machete_arm_1k.png",
                    "md5": "69a760a495bb0a10cbf0ab7a439ca8f0"
                },
                "exr": {
                    "size": 1778650,
                    "url": "https://dl.polyhaven.org/file/ph-assets/Models/exr/1k/machete/machete_arm_1k.exr",
                    "md5": "db11c2d2bb698ebb62b0f0d97277b64e"
                }
            }
        },
        "Rough": {
            "4k": {
                "jpg": {
                    "size": 9272829,
                    "url": "https://dl.polyhaven.org/file/ph-assets/Models/jpg/4k/machete/machete_rough_4k.jpg",
                    "md5": "99b1a217ef6c079f47e0feb01e32ad2e"
                },
                "png": {
                    "size": 12336549,
                    "url": "https://dl.polyhaven.org/file/ph-assets/Models/png/4k/machete/machete_rough_4k.png",
                    "md5": "65070afccd178476b232f430f314ba41"
                },
                "exr": {
                    "size": 11903675,
                    "url": "https://dl.polyhaven.org/file/ph-assets/Models/exr/4k/machete/machete_rough_4k.exr",
                    "md5": "dc6992550c93bc2bb1976358b2cd4a82"
                }
            },
            "2k": {
                "jpg": {
                    "size": 2415238,
                    "url": "https://dl.polyhaven.org/file/ph-assets/Models/jpg/2k/machete/machete_rough_2k.jpg",
                    "md5": "1fd0bc96aa31ba0dc419f42476205c67"
                },
                "png": {
                    "size": 4631832,
                    "url": "https://dl.polyhaven.org/file/ph-assets/Models/png/2k/machete/machete_rough_2k.png",
                    "md5": "68db61560d677ce11a26adb565a8bb4f"
                },
                "exr": {
                    "size": 3538397,
                    "url": "https://dl.polyhaven.org/file/ph-assets/Models/exr/2k/machete/machete_rough_2k.exr",
                    "md5": "d9764d6b013a343ea22728bac2b712f4"
                }
            },
            "1k": {
                "jpg": {
                    "size": 600488,
                    "url": "https://dl.polyhaven.org/file/ph-assets/Models/jpg/1k/machete/machete_rough_1k.jpg",
                    "md5": "849bd6a097620ef4e10a3b8d9a279eb5"
                },
                "png": {
                    "size": 1366343,
                    "url": "https://dl.polyhaven.org/file/ph-assets/Models/png/1k/machete/machete_rough_1k.png",
                    "md5": "a638ac98579869453eaaa43d4c7636a5"
                },
                "exr": {
                    "size": 997316,
                    "url": "https://dl.polyhaven.org/file/ph-assets/Models/exr/1k/machete/machete_rough_1k.exr",
                    "md5": "cf46ac08bade06d275dfcd6febb76885"
                }
            }
        },
        "AO": {
            "4k": {
                "jpg": {
                    "size": 2327893,
                    "url": "https://dl.polyhaven.org/file/ph-assets/Models/jpg/4k/machete/machete_ao_4k.jpg",
                    "md5": "6df1c212470f593354ca47bde87b3f53"
                },
                "png": {
                    "size": 7985322,
                    "url": "https://dl.polyhaven.org/file/ph-assets/Models/png/4k/machete/machete_ao_4k.png",
                    "md5": "1d30e505ebac7496308587c04b162deb"
                },
                "exr": {
                    "size": 4889278,
                    "url": "https://dl.polyhaven.org/file/ph-assets/Models/exr/4k/machete/machete_ao_4k.exr",
                    "md5": "53c2501a46dda603875f83058452c97c"
                }
            },
            "2k": {
                "jpg": {
                    "size": 535367,
                    "url": "https://dl.polyhaven.org/file/ph-assets/Models/jpg/2k/machete/machete_ao_2k.jpg",
                    "md5": "1c3d6762b9ca61a47096ce79e024e950"
                },
                "png": {
                    "size": 2816669,
                    "url": "https://dl.polyhaven.org/file/ph-assets/Models/png/2k/machete/machete_ao_2k.png",
                    "md5": "31ce81e9c88a8336cc6cc3e9680b6280"
                },
                "exr": {
                    "size": 1612613,
                    "url": "https://dl.polyhaven.org/file/ph-assets/Models/exr/2k/machete/machete_ao_2k.exr",
                    "md5": "6f7757aab3a837f688a22053ca7712e4"
                }
            },
            "1k": {
                "jpg": {
                    "size": 147643,
                    "url": "https://dl.polyhaven.org/file/ph-assets/Models/jpg/1k/machete/machete_ao_1k.jpg",
                    "md5": "ccb2b338f6f009201d4195e816b21a95"
                },
                "png": {
                    "size": 775534,
                    "url": "https://dl.polyhaven.org/file/ph-assets/Models/png/1k/machete/machete_ao_1k.png",
                    "md5": "47ebb612293dd85c423aeae8e7d31bbd"
                },
                "exr": {
                    "size": 433228,
                    "url": "https://dl.polyhaven.org/file/ph-assets/Models/exr/1k/machete/machete_ao_1k.exr",
                    "md5": "2523a99c2cc49fc028f6107061d4e759"
                }
            }
        }
    }
}